[
  {
    "id": "1",
    "title": "Doa Bangun Tidur",
    "category": "Doa Pagi",
    "arabic": "الْحَمْدُ لِلّٰهِ الَّذِيْ أَحْيَانَا بَعْدَ مَا أَمَاتَنَا وَإِلَيْهِ النُّشُوْرِ",
    "malay": "Segala puji bagi Allah yang telah menghidupkan kami setelah kami mati (dalam tidur) dan kepada-Nyalah kami dibangkitkan.",
    "icon": "wb_sunny",
    "color": "orange"
  },
  {
    "id": "2",
    "title": "Doa Masuk Rumah",
    "category": "Doa Lain-lain",
    "arabic": "بِسْمِ اللّٰهِ وَلَجْنَا وَبِسْمِ اللّٰهِ خَرَجْنَا وَعَلَى اللّٰهِ رَبِّنَا تَوَكَّلْنَا",
    "malay": "Dengan nama Allah kami masuk, dengan nama Allah kami keluar, dan kepada Allah Tuhan kami, kami bertawakal.",
    "icon": "home",
    "color": "blue"
  },
  {
    "id": "3",
    "title": "Doa Keluar Rumah",
    "category": "Doa Lain-lain",
    "arabic": "بِسْمِ اللّٰهِ تَوَكَّلْتُ عَلَى اللّٰهِ لَا حَوْلَ وَلَا قُوَّةَ إِلَّا بِاللّٰهِ",
    "malay": "Dengan nama Allah aku bertawakal kepada Allah, tiada daya dan kekuatan kecuali dengan pertolongan Allah.",
    "icon": "door_front_door",
    "color": "green"
  },
  {
    "id": "4",
    "title": "Doa Sebelum Makan",
    "category": "Doa Lain-lain",
    "arabic": "اللّٰهُمَّ بَارِكْ لَنَا فِيْمَا رَزَقْتَنَا وَقِنَا عَذَابَ النَّارِ",
    "malay": "Ya Allah, berkatilah rezeki yang Engkau berikan kepada kami dan peliharalah kami dari azab neraka.",
    "icon": "restaurant",
    "color": "red"
  },
  {
    "id": "5",
    "title": "Doa Selepas Makan",
    "category": "Doa Lain-lain",
    "arabic": "الْحَمْدُ لِلّٰهِ الَّذِيْ أَطْعَمَنَا وَسَقَانَا وَجَعَلَنَا مُسْلِمِيْنَ",
    "malay": "Segala puji bagi Allah yang telah memberi makan dan minum kepada kami, serta menjadikan kami orang-orang Islam.",
    "icon": "restaurant_menu",
    "color": "purple"
  },
  {
    "id": "6",
    "title": "Doa Masuk Masjid",
    "category": "Doa Selepas Solat",
    "arabic": "اللّٰهُمَّ افْتَحْ لِيْ أَبْوَابَ رَحْمَتِكَ",
    "malay": "Ya Allah, bukakanlah untukku pintu-pintu rahmat-Mu.",
    "icon": "mosque",
    "color": "teal"
  },
  {
    "id": "7",
    "title": "Doa Keluar Masjid",
    "category": "Doa Selepas Solat",
    "arabic": "اللّٰهُمَّ إِنِّيْ أَسْأَلُكَ مِنْ فَضْلِكَ",
    "malay": "Ya Allah, sesungguhnya aku memohon kepada-Mu dari kurnia-Mu.",
    "icon": "exit_to_app",
    "color": "indigo"
  },
  {
    "id": "8",
    "title": "Doa Tahajud",
    "category": "Doa Petang",
    "arabic": "اللّٰهُمَّ لَكَ الْحَمْدُ أَنْتَ نُوْرُ السَّمَاوَاتِ وَالْأَرْضِ وَلَكَ الْحَمْدُ أَنْتَ قَيِّمُ السَّمَاوَاتِ وَالْأَرْضِ",
    "malay": "Ya Allah, bagi-Mu segala puji. Engkaulah cahaya langit dan bumi. Dan bagi-Mu segala puji. Engkaulah yang mengurus langit dan bumi.",
    "icon": "nightlight_round",
    "color": "deepPurple"
  },
  {
    "id": "9",
    "title": "Doa Istikharah",
    "category": "Doa Lain-lain",
    "arabic": "اللّٰهُمَّ إِنِّيْ أَسْتَخِيْرُكَ بِعِلْمِكَ وَأَسْتَقْدِرُكَ بِقُدْرَتِكَ",
    "malay": "Ya Allah, sesungguhnya aku memohon petunjuk kepada-Mu dengan ilmu-Mu dan aku memohon kemampuan kepada-Mu dengan kekuasaan-Mu.",
    "icon": "lightbulb",
    "color": "amber"
  },
  {
    "id": "10",
    "title": "Doa Hajat",
    "category": "Doa Lain-lain",
    "arabic": "اللّٰهُمَّ إِنِّيْ أَسْأَلُكَ بِأَنَّ لَكَ الْحَمْدَ لَا إِلٰهَ إِلَّا أَنْتَ وَحْدَكَ لَا شَرِيْكَ لَكَ",
    "malay": "Ya Allah, sesungguhnya aku memohon kepada-Mu dengan (hakikat) bahawa bagi-Mu segala puji, tiada Tuhan melainkan Engkau semata, yang tiada sekutu bagi-Mu.",
    "icon": "star",
    "color": "pink"
  },
  {
    "id": "11",
    "title": "Doa Subuh",
    "category": "Doa Pagi",
    "arabic": "اللّٰهُمَّ إِنِّيْ أَسْأَلُكَ عِلْمًا نَافِعًا وَرِزْقًا طَيِّبًا وَعَمَلًا مُتَقَبَّلًا",
    "malay": "Ya Allah, sesungguhnya aku memohon kepada-Mu ilmu yang bermanfaat, rezeki yang baik, dan amal yang diterima.",
    "icon": "wb_twilight",
    "color": "cyan"
  },
  {
    "id": "12",
    "title": "Doa Maghrib",
    "category": "Doa Petang",
    "arabic": "اللّٰهُمَّ أَعِنِّيْ عَلَى ذِكْرِكَ وَشُكْرِكَ وَحُسْنِ عِبَادَتِكَ",
    "malay": "Ya Allah, tolonglah aku untuk selalu mengingat-Mu, bersyukur kepada-Mu, dan beribadah kepada-Mu dengan baik.",
    "icon": "wb_sunset",
    "color": "orange"
  },
  {
    "id": "13",
    "title": "Doa Isyak",
    "category": "Doa Petang",
    "arabic": "اللّٰهُمَّ إِنِّيْ أَعُوْذُ بِكَ مِنْ ضِيْقِ الْقَبْرِ وَأَعُوْذُ بِكَ مِنْ فِتْنَةِ الدَّجَّالِ",
    "malay": "Ya Allah, sesungguhnya aku berlindung kepada-Mu dari kesempitan kubur dan aku berlindung kepada-Mu dari fitnah Dajjal.",
    "icon": "bedtime",
    "color": "blueGrey"
  },
  {
    "id": "14",
    "title": "Doa Ketika Hujan",
    "category": "Doa Lain-lain",
    "arabic": "اللّٰهُمَّ صَيِّبًا نَافِعًا",
    "malay": "Ya Allah, turunkanlah hujan yang bermanfaat.",
    "icon": "water_drop",
    "color": "lightBlue"
  },
  {
    "id": "15",
    "title": "Doa Ketika Sakit",
    "category": "Doa Lain-lain",
    "arabic": "اللّٰهُمَّ رَبَّ النَّاسِ أَذْهِبِ الْبَأْسَ وَاشْفِ أَنْتَ الشَّافِيْ لَا شِفَاءَ إِلَّا شِفَاؤُكَ شِفَاءً لَا يُغَادِرُ سَقَمًا",
    "malay": "Ya Allah, Tuhan manusia, hilangkanlah penyakit ini dan sembuhkanlah. Engkaulah Yang Maha Penyembuh. Tiada kesembuhan kecuali kesembuhan dari-Mu, kesembuhan yang tidak meninggalkan penyakit sedikitpun.",
    "icon": "local_hospital",
    "color": "red"
  },
  {
    "id": "16",
    "title": "Doa Untuk Kedua Ibu Bapa",
    "category": "Doa Keluarga",
    "arabic": "رَبِّ ارْحَمْهُمَا كَمَا رَبَّيَانِيْ صَغِيْرًا",
    "malay": "Ya Tuhanku, sayangilah kedua ibu bapaku sebagaimana mereka menyayangiku semasa aku kecil.",
    "icon": "family_restroom",
    "color": "deepOrange"
  },
  {
    "id": "17",
    "title": "Doa Untuk Anak",
    "category": "Doa Keluarga",
    "arabic": "اللّٰهُمَّ اجْعَلْهُ بَارًا بِوَالِدَيْهِ وَذُرِّيَّةً طَيِّبَةً",
    "malay": "Ya Allah, jadikanlah anak ini baik kepada ibu bapanya dan jadikanlah zuriatnya yang baik.",
    "icon": "child_care",
    "color": "purple"
  },
  {
    "id": "18",
    "title": "Doa Sebelum Belajar",
    "category": "Doa Lain-lain",
    "arabic": "رَبِّ زِدْنِيْ عِلْمًا وَارْزُقْنِيْ فَهْمًا",
    "malay": "Ya Tuhanku, tambahkanlah ilmuku dan berilah aku kefahaman.",
    "icon": "school",
    "color": "green"
  },
  {
    "id": "19",
    "title": "Doa Selepas Belajar",
    "category": "Doa Lain-lain",
    "arabic": "اللّٰهُمَّ انْفَعْنِيْ بِمَا عَلَّمْتَنِيْ وَعَلِّمْنِيْ مَا يَنْفَعُنِيْ",
    "malay": "Ya Allah, berikanlah manfaat kepadaku dari apa yang telah Engkau ajarkan kepadaku dan ajarkanlah kepadaku apa yang bermanfaat bagiku.",
    "icon": "menu_book",
    "color": "indigo"
  },
  {
    "id": "20",
    "title": "Doa Naik Kenderaan",
    "category": "Doa Lain-lain",
    "arabic": "سُبْحَانَ الَّذِيْ سَخَّرَ لَنَا هٰذَا وَمَا كُنَّا لَهُ مُقْرِنِيْنَ وَإِنَّا إِلَىٰ رَبِّنَا لَمُنْقَلِبُوْنَ",
    "malay": "Maha Suci Allah yang telah menundukkan semua ini untuk kami, padahal kami tidak mampu menguasainya. Dan sesungguhnya kami akan kembali kepada Tuhan kami.",
    "icon": "directions_car",
    "color": "brown"
  }
  ,
  {
    "id": "21",
    "title": "Doa Sebelum Tidur",
    "category": "Doa Petang",
    "arabic": "بِاسْمِكَ اللَّهُمَّ أَمُوتُ وَأَحْيَا",
    "malay": "Dengan nama-Mu ya Allah, aku mati dan aku hidup kembali.",
    "icon": "bedtime",
    "color": "blueGrey"
  },
  {
    "id": "22",
    "title": "Doa Masuk Tandas",
    "category": "Doa Lain-lain",
    "arabic": "اللّٰهُمَّ إِنِّيْ أَعُوذُ بِكَ مِنَ الْخُبْثِ وَالْخَبَائِثِ",
    "malay": "Ya Allah, aku berlindung kepada-Mu dari kekotoran dan makhluk yang jahat.",
    "icon": "water_drop",
    "color": "lightBlue"
  },
  {
    "id": "23",
    "title": "Doa Keluar Tandas",
    "category": "Doa Lain-lain",
    "arabic": "غُفْرَانَكَ",
    "malay": "Aku memohon keampunan-Mu.",
    "icon": "exit_to_app",
    "color": "indigo"
  },
  {
    "id": "24",
    "title": "Doa Sebelum Wuduk",
    "category": "Doa Lain-lain",
    "arabic": "بِسْمِ اللَّهِ",
    "malay": "Dengan nama Allah (saat berwuduk).",
    "icon": "water_drop",
    "color": "teal"
  },
  {
    "id": "25",
    "title": "Doa Selepas Wuduk",
    "category": "Doa Lain-lain",
    "arabic": "اللَّهُمَّ اجْعَلْنِيْ مِنَ التَّوَّابِيْنَ وَمِنَ الْمُتَطَهِّرِيْنَ",
    "malay": "Ya Allah, jadikanlah aku termasuk orang yang sering bertaubat dan yang suci.",
    "icon": "mosque",
    "color": "teal"
  },
  {
    "id": "26",
    "title": "Doa Memohon Perlindungan",
    "category": "Doa Lain-lain",
    "arabic": "أَعُوذُ بِاللَّهِ مِنَ الشَّيْطَانِ الرَّجِيمِ",
    "malay": "Aku berlindung kepada Allah dari syaitan yang direjam.",
    "icon": "star",
    "color": "pink"
  }
  ,
  {
    "id": "27",
    "title": "Doa Memohon Rezeki",
    "category": "Doa Lain-lain",
    "arabic": "رَبِّ إِنِّي لِمَا أَنْزَلْتَ إِلَيَّ مِنْ خَيْرٍ فَقِيرٌ",
    "malay": "Tuhanku, sesungguhnya aku sangat memerlukan kurniaan rezeki yang Engkau turunkan kepadaku.",
    "icon": "star",
    "color": "green"
  },
  {
    "id": "28",
    "title": "Doa Ketika Sedih",
    "category": "Doa Lain-lain",
    "arabic": "اللّهم إني أعوذ بك من الهم والحزن",
    "malay": "Ya Allah, aku berlindung kepada-Mu dari kesusahan dan kesedihan.",
    "icon": "lightbulb",
    "color": "purple"
  },
  {
    "id": "29",
    "title": "Doa Dalam Perjalanan",
    "category": "Doa Lain-lain",
    "arabic": "اللَّهُمَّ أَنْتَ الصَّاحِبُ فِي السَّفَرِ وَالْخَلِيفَةُ فِي الْأَهْلِ",
    "malay": "Ya Allah, Engkaulah teman ketika perjalanan dan pemelihara bagi keluarga.",
    "icon": "directions_car",
    "color": "brown"
  },
  {
    "id": "30",
    "title": "Doa Untuk Anak Selamat",
    "category": "Doa Keluarga",
    "arabic": "رَبِّ احْفَظْهُمْ مِنْ كُلِّ سُوءٍ",
    "malay": "Tuhanku, peliharalah mereka dari segala keburukan.",
    "icon": "child_care",
    "color": "purple"
  },
  {
    "id": "31",
    "title": "Doa Memohon Berkat Rumah",
    "category": "Doa Lain-lain",
    "arabic": "اللَّهُمَّ بَارِكْ لِهَذَا الْبَيْتِ وَأَهْلِهِ",
    "malay": "Ya Allah, berkati rumah ini dan penghuni-penghuninya.",
    "icon": "home",
    "color": "blue"
  },
  {
    "id": "32",
    "title": "Doa Taubat (Memohon Ampun)",
    "category": "Doa Lain-lain",
    "arabic": "رَبِّ اغْفِرْ لِيْ ذُنُوبِيْ",
    "malay": "Tuhanku, ampunilah dosa-dosaku.",
    "icon": "star",
    "color": "pink"
  }
]